README.md
setup.py
Hanalytics_python_package.egg-info/PKG-INFO
Hanalytics_python_package.egg-info/SOURCES.txt
Hanalytics_python_package.egg-info/dependency_links.txt
Hanalytics_python_package.egg-info/requires.txt
Hanalytics_python_package.egg-info/top_level.txt
hanalytics/hanalytics_ga4/__init__.py
hanalytics/hanalytics_ga4/connectga4.py
hanalytics/hanalytics_ga4/tools.py
hanalytics/hanalytics_keywords_generator/googleAds_keywords.py
hanalytics/hanalytics_ua/__init__.py
hanalytics/hanalytics_ua/connect.py
hanalytics/hanalytics_ua/customs.py
hanalytics/hanalytics_ua/query.py
hanalytics/hanalytics_ua/reports.py