Metadata-Version: 2.1
Name: Hanalytics-python-package
Version: 0.3
Summary: Useful tools for GA3 & GA4 and Google ADs generator
Home-page: UNKNOWN
Author: Hanalytics
License: UNKNOWN
Platform: UNKNOWN
